penguin_py/__init__.py
penguin_py/penguin_py.py
penguin_py/colours/__init__.py
penguin_py/colours/colour_map.py
penguin_py/colours/get_default_colours.py
penguin_py/colours/get_logger_colour.py
penguin_py/logs/__init__.py
penguin_py/logs/log_args.py
penguin_py/logs/log_return.py
penguin_py/processing/__init__.py
penguin_py/processing/get_time_msg.py
penguin_py/processing/processing.py
penguin_py-0.3.14.dist-info/LICENSE
penguin_py-0.3.14.dist-info/METADATA
penguin_py-0.3.14.dist-info/WHEEL
penguin_py-0.3.14.dist-info/top_level.txt
penguin_py-0.3.14.dist-info/RECORD
