Metadata-Version: 2.1
Name: penguin-py
Version: 0.3.14
Summary: Penguin: a customizable stopwatch decorator
Home-page: https://github.com/espitiaandres/penguin
Download-URL: https://github.com/espitiaandres/penguin
Author: espitiaandres
Author-email: espitiaandres123@gmail.com
Project-URL: Documentation, https://github.com/espitiaandres/penguin
Project-URL: Source, https://github.com/espitiaandres/penguin
Project-URL: Tracker, https://github.com/espitiaandres/penguin/issues
Keywords: penguin python,penguin_py,stopwatch,timer,penguin_py timer
Classifier: Programming Language :: Python :: 3
Classifier: License :: OSI Approved :: MIT License
Classifier: Operating System :: OS Independent
Classifier: Topic :: Utilities
Requires-Python: >=3.7
License-File: LICENSE
Requires-Dist: pre-commit
Requires-Dist: colorama==0.4.6
